dimeai/__init__.py
dimeai/agent.py
dimeai/benchmark.py
dimeai/cli.py
dimeai/collection.py
dimeai/config.py
dimeai/dossier.py
dimeai/dossier_session.py
dimeai/extraction.py
dimeai/features.py
dimeai/interactive.py
dimeai/simulation.py
dimeai/training.py
dimeai/web_collector.py
dimeai-0.1.0.dist-info/METADATA
dimeai-0.1.0.dist-info/WHEEL
dimeai-0.1.0.dist-info/entry_points.txt
dimeai-0.1.0.dist-info/licenses/LICENSE
dimeai-0.1.0.dist-info/RECORD
