Metadata-Version: 2.4
Name: dimeai
Version: 0.1.0
Summary: DIMEFIL Analyst CLI - AI-powered geopolitical event analysis using temporal graph networks
Project-URL: Homepage, https://github.com/dimeai/dimeai
Project-URL: Documentation, https://github.com/dimeai/dimeai#readme
Project-URL: Repository, https://github.com/dimeai/dimeai
Project-URL: Issues, https://github.com/dimeai/dimeai/issues
Author-email: DimeAI Team <dimeai@example.com>
License: MIT
License-File: LICENSE
Keywords: cli,dimefil,entity-extraction,geopolitics,graph-neural-networks,nlp,security-analysis,temporal-graphs
Classifier: Development Status :: 3 - Alpha
Classifier: Environment :: Console
Classifier: Intended Audience :: Developers
Classifier: Intended Audience :: Science/Research
Classifier: License :: OSI Approved :: MIT License
Classifier: Operating System :: OS Independent
Classifier: Programming Language :: Python :: 3
Classifier: Programming Language :: Python :: 3.10
Classifier: Programming Language :: Python :: 3.11
Classifier: Programming Language :: Python :: 3.12
Classifier: Topic :: Scientific/Engineering :: Artificial Intelligence
Classifier: Topic :: Scientific/Engineering :: Information Analysis
Requires-Python: >=3.10
Requires-Dist: click>=8.1.0
Requires-Dist: ddgs>=6.0.0
Requires-Dist: gliner2>=0.1.0
Requires-Dist: httpx>=0.25.0
Requires-Dist: networkx>=3.0
Requires-Dist: numpy>=1.24.0
Requires-Dist: pyyaml>=6.0
Requires-Dist: rich>=13.0.0
Requires-Dist: scikit-learn>=1.3.0
Requires-Dist: sentence-transformers>=2.2.0
Requires-Dist: torch-geometric>=2.4.0
Requires-Dist: torch>=2.0.0
Provides-Extra: agent
Requires-Dist: boto3>=1.28.0; extra == 'agent'
Requires-Dist: strands-agents>=0.1.0; extra == 'agent'
Provides-Extra: all
Requires-Dist: black>=23.0.0; extra == 'all'
Requires-Dist: boto3>=1.28.0; extra == 'all'
Requires-Dist: hypothesis>=6.0.0; extra == 'all'
Requires-Dist: mypy>=1.0.0; extra == 'all'
Requires-Dist: pytest-cov>=4.0.0; extra == 'all'
Requires-Dist: pytest>=7.0.0; extra == 'all'
Requires-Dist: ruff>=0.1.0; extra == 'all'
Requires-Dist: strands-agents>=0.1.0; extra == 'all'
Provides-Extra: dev
Requires-Dist: black>=23.0.0; extra == 'dev'
Requires-Dist: hypothesis>=6.0.0; extra == 'dev'
Requires-Dist: mypy>=1.0.0; extra == 'dev'
Requires-Dist: pytest-cov>=4.0.0; extra == 'dev'
Requires-Dist: pytest>=7.0.0; extra == 'dev'
Requires-Dist: ruff>=0.1.0; extra == 'dev'
